{
	"info": {
		"_postman_id": "59464f6b-1e26-4202-96d4-a97e4dca96d7",
		"name": "Ejercicios curso Spring s 4, 5 y 6",
		"schema": "https://schema.getpostman.com/json/collection/v2.1.0/collection.json",
		"_exporter_id": "16317252"
	},
	"item": [
		{
			"name": "/hola",
			"request": {
				"method": "GET",
				"header": [],
				"url": {
					"raw": "http://localhost:8080/hola",
					"protocol": "http",
					"host": [
						"localhost"
					],
					"port": "8080",
					"path": [
						"hola"
					]
				}
			},
			"response": []
		},
		{
			"name": "/api/latops",
			"request": {
				"method": "GET",
				"header": [],
				"url": {
					"raw": "http://localhost:8080/api/latops",
					"protocol": "http",
					"host": [
						"localhost"
					],
					"port": "8080",
					"path": [
						"api",
						"latops"
					]
				}
			},
			"response": []
		},
		{
			"name": "/api/latops",
			"request": {
				"method": "POST",
				"header": [],
				"body": {
					"mode": "raw",
					"raw": "{\r\n    \"mark\": \"Asus\",\r\n    \"model\": \"New pepine\",\r\n    \"yearr\": 2023,\r\n    \"sn\": \"123abc\"\r\n}",
					"options": {
						"raw": {
							"language": "json"
						}
					}
				},
				"url": {
					"raw": "http://localhost:8080/api/latops",
					"protocol": "http",
					"host": [
						"localhost"
					],
					"port": "8080",
					"path": [
						"api",
						"latops"
					]
				}
			},
			"response": []
		}
	]
}